wuba_wos/__init__.py
wuba_wos/__main__.py
wuba_wos/py.typed
wuba_wos-0.1.2.dist-info/METADATA
wuba_wos-0.1.2.dist-info/WHEEL
wuba_wos-0.1.2.dist-info/entry_points.txt
wuba_wos-0.1.2.dist-info/RECORD
