Metadata-Version: 2.4
Name: wuba_wos
Version: 0.1.2
Summary: 五八WOS平台skd
Author-email: 王梦迪 <wangmengdi06@58.com>
Requires-Python: >=3.10
Requires-Dist: loguru>=0.7.3
Requires-Dist: requests>=2.32.4
